cortalinsight/__init__.py
cortalinsight/api.py
cortalinsight/cli.py
cortalinsight/exceptions.py
cortalinsight/utils.py
cortalinsight-0.1.6.dist-info/LICENSE
cortalinsight-0.1.6.dist-info/METADATA
cortalinsight-0.1.6.dist-info/WHEEL
cortalinsight-0.1.6.dist-info/entry_points.txt
cortalinsight-0.1.6.dist-info/top_level.txt
cortalinsight-0.1.6.dist-info/RECORD
