Metadata-Version: 2.1
Name: cortalinsight
Version: 0.1.6
Summary: A command line tool to interact with Cortal Insight API
Home-page: http://cortalinsight.com
Author: Preetham
Author-email: developer@cortalinsight.com
Project-URL: Source Code, https://github.com/cortal-insight/cortal-insight-python-client
Keywords: cortal insight cli api
Classifier: Development Status :: 3 - Alpha
Classifier: Intended Audience :: Developers
Classifier: Topic :: Software Development :: Build Tools
Classifier: License :: OSI Approved :: MIT License
Classifier: Programming Language :: Python :: 3
Classifier: Programming Language :: Python :: 3.8
License-File: LICENSE
Requires-Dist: requests >=2.25
Requires-Dist: tqdm ==4.66.1
Requires-Dist: opencv-python >=4.1
Requires-Dist: PyYAML >=6.0
